setup.cfg
setup.py
osf/__init__.py
osf/classes.py
osf/grammar.py
osf/objectify.py
osf/parse.py
osf/timeutils.py
osf.egg-info/PKG-INFO
osf.egg-info/SOURCES.txt
osf.egg-info/dependency_links.txt
osf.egg-info/requires.txt
osf.egg-info/top_level.txt
test/test_classes.py
test/test_objectifier.py
test/test_parser.py
test/test_real.py
test/test_timeutils.py