Metadata-Version: 1.0
Name: osf
Version: 1.12
Summary: OSF in python
Home-page: https://github.com/luto/osf.py
Author: luto
Author-email: m@luto.at
License: AGPLv3
Platform: UNKNOWN
